aionet/__init__.py
aionet/constants.py
aionet/dispatcher.py
aionet/exceptions.py
aionet/logging.py
aionet/utils.py
aionet/version.py
aionet/connections/__init__.py
aionet/connections/base.py
aionet/connections/interface.py
aionet/connections/serial.py
aionet/connections/ssh.py
aionet/connections/telnet.py
aionet/vendors/__init__.py
aionet/vendors/devices/__init__.py
aionet/vendors/devices/base.py
aionet/vendors/devices/base_comware.py
aionet/vendors/devices/base_ios.py
aionet/vendors/devices/base_junos.py
aionet/vendors/devices/arista/__init__.py
aionet/vendors/devices/arista/arista_eos.py
aionet/vendors/devices/aruba/__init__.py
aionet/vendors/devices/aruba/aruba_aos_6.py
aionet/vendors/devices/aruba/aruba_aos_8.py
aionet/vendors/devices/cisco/__init__.py
aionet/vendors/devices/cisco/cisco_asa.py
aionet/vendors/devices/cisco/cisco_ios.py
aionet/vendors/devices/cisco/cisco_iosxr.py
aionet/vendors/devices/cisco/cisco_nxos.py
aionet/vendors/devices/fujitsu/__init__.py
aionet/vendors/devices/fujitsu/fujitsu_switch.py
aionet/vendors/devices/hp/__init__.py
aionet/vendors/devices/hp/hp_comware.py
aionet/vendors/devices/hp/hp_comware_limited.py
aionet/vendors/devices/juniper/__init__.py
aionet/vendors/devices/juniper/juniper_junos.py
aionet/vendors/devices/mikrotik/__init__.py
aionet/vendors/devices/mikrotik/mikrotik_routeros.py
aionet/vendors/devices/terminal/__init__.py
aionet/vendors/devices/terminal/terminal.py
aionet/vendors/devices/ubiquiti/__init__.py
aionet/vendors/devices/ubiquiti/ubiquity_edge.py
aionet/vendors/terminal_modes/__init__.py
aionet/vendors/terminal_modes/aruba.py
aionet/vendors/terminal_modes/base.py
aionet/vendors/terminal_modes/cisco.py
aionet/vendors/terminal_modes/fujitsu.py
aionet/vendors/terminal_modes/hp.py
aionet/vendors/terminal_modes/juniper.py
aionet/vendors/terminal_modes/mikrotik.py
aionet/vendors/terminal_modes/uniquiti.py
aionet-0.0.43.dist-info/METADATA
aionet-0.0.43.dist-info/WHEEL
aionet-0.0.43.dist-info/top_level.txt
aionet-0.0.43.dist-info/RECORD
