Metadata-Version: 2.1
Name: aionet
Version: 0.0.43
Summary: async networking SDK
Home-page: https://github.com/Ali-aqrabawi/aionet
Author: ali aqrabawi
Author-email: aaqrabaw@gmail.com
License: UNKNOWN
Platform: UNKNOWN
Classifier: Development Status :: 4 - Beta
Classifier: Programming Language :: Python :: 3
Classifier: License :: OSI Approved :: MIT License
Classifier: Operating System :: OS Independent
Requires-Dist: textfsm (==0.4.1)
Requires-Dist: asyncssh
